ocrspace/__init__.py
ocrspace/auth.py
ocrspace/client.py
ocrspace/errors.py
ocrspace/models.py
ocrspace/utils.py
ocrspace_sdk_upgraded-0.2.0.dist-info/METADATA
ocrspace_sdk_upgraded-0.2.0.dist-info/WHEEL
ocrspace_sdk_upgraded-0.2.0.dist-info/top_level.txt
ocrspace_sdk_upgraded-0.2.0.dist-info/RECORD
