Metadata-Version: 2.4
Name: ocrspace-sdk-upgraded
Version: 0.2.0
Summary: Upgraded OCR.Space Python SDK (file/url/bytes/base64, errors, auth, examples)
Author: Nguyen Truong Dat
Author-email: You <you@example.com>
Requires-Python: >=3.8
Requires-Dist: requests>=2.28
